{
  "ComponentIndexes": {},
  "ControlUniqueIds": {
    "App": 1,
    "Button1": 26,
    "Button2": 27,
    "Button3": 34,
    "DataCardKey1": 8,
    "DataCardKey2": 13,
    "DataCardKey3": 18,
    "DataCardKey4": 23,
    "DataCardKey5": 45,
    "DataCardValue1": 9,
    "DataCardValue2": 14,
    "DataCardValue3": 19,
    "DataCardValue4": 24,
    "DataCardValue5": 46,
    "Date_DataCard1": 11,
    "ErrorMessage1": 10,
    "ErrorMessage2": 15,
    "ErrorMessage3": 20,
    "ErrorMessage4": 25,
    "ErrorMessage5": 47,
    "Form1": 5,
    "Form2": 42,
    "GUI_DataCard1": 43,
    "Icon1": 40,
    "Icon2": 36,
    "iconCheck1": 38,
    "iconCircle1": 37,
    "Image1": 4,
    "Image4": 29,
    "Label1": 32,
    "Label2": 31,
    "Label3": 30,
    "Label4": 33,
    "LblSuccessMsg1": 39,
    "Location_DataCard1": 21,
    "Screen1": 3,
    "Screen2": 35,
    "Screen3": 28,
    "Screen5": 41,
    "StarVisible1": 7,
    "StarVisible2": 12,
    "StarVisible3": 17,
    "StarVisible4": 22,
    "StarVisible5": 44,
    "Time _DataCard1": 16,
    "UserName_DataCard1": 6
  },
  "FunctionParamsInvariantScripts": {},
  "FunctionParamsInvariantScriptsOnInstances": {},
  "HeaderLastSavedDateTimeUTC": "06/24/2022 16:52:27",
  "IsLegacyComponentAllowGlobalScopeCase": false,
  "LocalConnectionIDReferences": {
    "20ca9c64-4a00-4099-be10-12f2a60c383d": "\"/providers/microsoft.powerapps/apis/shared_powerappsnotification/connections/21776a4402cc448fbc5b8b888fe1521c\"",
    "6743c71c-0d61-4f7c-95c9-7d368855afae": "\"/providers/microsoft.powerapps/apis/shared_bingmaps/connections/badeefe825b24f88b683f1e5e9510c2a\"",
    "b156cc4c-47ce-4438-a9da-e4f1139666e3": "\"/providers/microsoft.powerapps/apis/shared_onedrive/connections/3b4b13a20eed4bde95a69d5da1a1eeb7\"",
    "cc04ec0b-8485-4f2c-b0d7-cc7986f4780f": "\"/providers/microsoft.powerapps/apis/shared_gmail/connections/92fa456d45e84576b2d6c268cf7f8ef6\"",
    "e3f0fda8-c202-4bb0-9b2b-2fdc67635308": "\"/providers/microsoft.powerapps/apis/shared_excel/connections/544ced37724049ba9c9885a669a0246b\""
  },
  "LocalDatabaseReferencesAsEmpty": false,
  "LocalResourceFileNames": {
    "Coat_of_arms_of_Ghana.svg": "2e86016c-8ed9-4be8-809e-9be3c2d0361b.png"
  },
  "LocalResourceRootPaths": {
    "Coat_of_arms_of_Ghana.svg": "https://docserverpwaprodwus.blob.core.windows.net/5bc80f4a-0adf-4152-8242-f00b1de3f830-1/resource/Assets0Images02e86016c-8ed9-4be8-809e-9be3c2d0361b.png?sv=2017-04-17&sr=b&sig=xZmnI1BphY38Gn2bHQvIittH6YtGMFM7ZrP%2FgCKxL6I%3D&spr=https&se=2022-06-25T17%3A01%3A43Z&sp=r"
  },
  "OldLogoFileName": "zpoqbg1c.jpg",
  "OrderComponentMetadata": {},
  "OrderComponentTemplate": {},
  "OrderDataSource": {
    "BingMaps": 0,
    "Collection1": 5,
    "CustomGallerySample": 4,
    "Gmail": 2,
    "PowerAppsNotification": 1,
    "Table1": 3
  },
  "OrderGroupControls": {},
  "OrderPcfTemplate": {},
  "OrderTemplate": {},
  "OrderXMLTemplate": {
    "button": 4,
    "circle": 6,
    "form": 1,
    "icon": 5,
    "image": 0,
    "label": 2,
    "text": 3
  },
  "PublishOrderIndices": {
    "App": 0,
    "Button1": 28,
    "Button2": 29,
    "Button3": 5,
    "DataCardKey1": 10,
    "DataCardKey2": 15,
    "DataCardKey3": 20,
    "DataCardKey4": 25,
    "DataCardKey5": 38,
    "DataCardValue1": 11,
    "DataCardValue2": 16,
    "DataCardValue3": 21,
    "DataCardValue4": 26,
    "DataCardValue5": 39,
    "Date_DataCard1": 13,
    "ErrorMessage1": 12,
    "ErrorMessage2": 17,
    "ErrorMessage3": 22,
    "ErrorMessage4": 27,
    "ErrorMessage5": 40,
    "Form1": 7,
    "Form2": 35,
    "GUI_DataCard1": 36,
    "Icon1": 34,
    "Icon2": 30,
    "iconCheck1": 32,
    "iconCircle1": 31,
    "Image1": 6,
    "Image4": 0,
    "Label1": 3,
    "Label2": 2,
    "Label3": 1,
    "Label4": 4,
    "LblSuccessMsg1": 33,
    "Location_DataCard1": 23,
    "Screen1": 0,
    "Screen2": 0,
    "Screen3": 0,
    "Screen5": 0,
    "StarVisible1": 9,
    "StarVisible2": 14,
    "StarVisible3": 19,
    "StarVisible4": 24,
    "StarVisible5": 37,
    "Time _DataCard1": 18,
    "UserName_DataCard1": 8
  },
  "ResourcesJsonIndices": {
    "Image-Coat_of_arms_of_Ghana.svg": 1,
    "Image-SampleImage": 0
  },
  "RuleScreenIdWithoutScreen": {},
  "TemplateVersions": {},
  "VolatileProperties": {
    "AnalysisLoadTime": 0.4164588,
    "ControlCount": {
      "button": 3,
      "circle": 1,
      "form": 2,
      "icon": 3,
      "image": 2,
      "label": 20,
      "screen": 4,
      "text": 5,
      "typedDataCard": 5
    },
    "DeserializationLoadTime": 1.2219552,
    "ErrorCount": 1
  },
  "WasLocalDatabaseReferencesEmpty": true
}